dsul/__init__.py
dsul/distributions.py
dsul/linear_model.py
dsul/confidence_intervals/__init__.py
dsul/confidence_intervals/analytical.py
dsul/confidence_intervals/base.py
dsul/confidence_intervals/computational.py
tests/__init__.py
tests/test_confidence_intervals.py
tests/test_linear_model.py
DSUL-0.0.1.dist-info/LICENSE
DSUL-0.0.1.dist-info/METADATA
DSUL-0.0.1.dist-info/WHEEL
DSUL-0.0.1.dist-info/top_level.txt
DSUL-0.0.1.dist-info/RECORD
